[
  {
    "id": "EBS:1063:7014_2026-07-12",
    "journey_id": "EBS:1063:7014",
    "datum": "2026-07-12",
    "lijn": "63",
    "lijnkleur": "#004899",
    "categorie": "M-net",
    "status": "cancelled",
    "oorzaak_categorieen": [
      "Personeel",
      "Logistiek"
    ],
    "oorzaak_raw": "Cause: Personeel, Logistiek",
    "terminus_alert": null,
    "advies": null,
    "haltes": [
      {
        "halte_id": "NL:S:37223552",
        "halte_naam": "De Vlinder",
        "geplande_tijd": "12:21",
        "vertraging_min": 0,
        "status": "cancelled",
        "vertrokken": false,
        "realtime": false,
        "platform": "Perron E",
        "bestemming": "Assendelft"
      }
    ],
    "eerste_tijd": "12:21",
    "dagdeel": "dal",
    "bijgewerkt": "2026-07-12 09:45:32",
    "eerst_gezien": "2026-07-12 09:45:32"
  },
  {
    "id": "EBS:1063:7014_2026-07-12",
    "journey_id": "EBS:1063:7014",
    "datum": "2026-07-12",
    "lijn": "63",
    "lijnkleur": "#004899",
    "categorie": "M-net",
    "status": "cancelled",
    "oorzaak_categorieen": [
      "Personeel",
      "Logistiek"
    ],
    "oorzaak_raw": "Cause: Personeel, Logistiek",
    "terminus_alert": null,
    "advies": null,
    "haltes": [
      {
        "halte_id": "NL:S:37223552",
        "halte_naam": "De Vlinder",
        "geplande_tijd": "12:21",
        "vertraging_min": 0,
        "status": "cancelled",
        "vertrokken": false,
        "realtime": false,
        "platform": "Perron E",
        "bestemming": "Assendelft"
      }
    ],
    "eerste_tijd": "12:21",
    "dagdeel": "dal",
    "bijgewerkt": "2026-07-12 10:01:09",
    "eerst_gezien": "2026-07-12 10:01:09"
  },
  {
    "id": "EBS:1391:7025_2026-07-12",
    "journey_id": "EBS:1391:7025",
    "datum": "2026-07-12",
    "lijn": "391",
    "lijnkleur": "#e1251b",
    "categorie": "R-net",
    "status": "cancelled",
    "oorzaak_categorieen": [
      "Personeel",
      "Logistiek"
    ],
    "oorzaak_raw": "Cause: Personeel, Logistiek",
    "terminus_alert": null,
    "advies": null,
    "haltes": [
      {
        "halte_id": "NL:S:37223552",
        "halte_naam": "De Vlinder",
        "geplande_tijd": "12:09",
        "vertraging_min": 0,
        "status": "cancelled",
        "vertrokken": false,
        "realtime": false,
        "platform": "Perron D",
        "bestemming": "Zaandam ZMC"
      }
    ],
    "eerste_tijd": "12:09",
    "dagdeel": "dal",
    "bijgewerkt": "2026-07-12 09:45:32",
    "eerst_gezien": "2026-07-12 09:45:32"
  },
  {
    "id": "EBS:1391:7025_2026-07-12",
    "journey_id": "EBS:1391:7025",
    "datum": "2026-07-12",
    "lijn": "391",
    "lijnkleur": "#e1251b",
    "categorie": "R-net",
    "status": "cancelled",
    "oorzaak_categorieen": [
      "Personeel",
      "Logistiek"
    ],
    "oorzaak_raw": "Cause: Personeel, Logistiek",
    "terminus_alert": null,
    "advies": null,
    "haltes": [
      {
        "halte_id": "NL:S:37223552",
        "halte_naam": "De Vlinder",
        "geplande_tijd": "12:09",
        "vertraging_min": 0,
        "status": "cancelled",
        "vertrokken": false,
        "realtime": false,
        "platform": "Perron D",
        "bestemming": "Zaandam ZMC"
      }
    ],
    "eerste_tijd": "12:09",
    "dagdeel": "dal",
    "bijgewerkt": "2026-07-12 10:01:09",
    "eerst_gezien": "2026-07-12 10:01:09"
  },
  {
    "id": "EBS:1111:7029_2026-07-12",
    "journey_id": "EBS:1111:7029",
    "datum": "2026-07-12",
    "lijn": "111",
    "lijnkleur": "#004899",
    "categorie": "M-net",
    "status": "cancelled",
    "oorzaak_categorieen": [
      "Personeel",
      "Logistiek"
    ],
    "oorzaak_raw": "Cause: Personeel, Logistiek",
    "terminus_alert": null,
    "advies": null,
    "haltes": [
      {
        "halte_id": "NL:S:37223552",
        "halte_naam": "De Vlinder",
        "geplande_tijd": "11:34",
        "vertraging_min": 0,
        "status": "cancelled",
        "vertrokken": false,
        "realtime": false,
        "platform": "Perron E",
        "bestemming": "Amsterdam Noord"
      }
    ],
    "eerste_tijd": "11:34",
    "dagdeel": "dal",
    "bijgewerkt": "2026-07-12 09:31:02",
    "eerst_gezien": "2026-07-12 09:31:02"
  },
  {
    "id": "EBS:1391:7024_2026-07-12",
    "journey_id": "EBS:1391:7024",
    "datum": "2026-07-12",
    "lijn": "391",
    "lijnkleur": "#e1251b",
    "categorie": "R-net",
    "status": "cancelled",
    "oorzaak_categorieen": [
      "Personeel",
      "Logistiek"
    ],
    "oorzaak_raw": "Cause: Personeel, Logistiek",
    "terminus_alert": null,
    "advies": null,
    "haltes": [
      {
        "halte_id": "NL:S:37223552",
        "halte_naam": "De Vlinder",
        "geplande_tijd": "11:18",
        "vertraging_min": 0,
        "status": "cancelled",
        "vertrokken": false,
        "realtime": false,
        "platform": "Perron C",
        "bestemming": "Amsterdam Centraal"
      }
    ],
    "eerste_tijd": "11:18",
    "dagdeel": "dal",
    "bijgewerkt": "2026-07-12 09:15:36",
    "eerst_gezien": "2026-07-12 09:15:36"
  },
  {
    "id": "EBS:1111:7021_2026-07-12",
    "journey_id": "EBS:1111:7021",
    "datum": "2026-07-12",
    "lijn": "111",
    "lijnkleur": "#004899",
    "categorie": "M-net",
    "status": "cancelled",
    "oorzaak_categorieen": [
      "Personeel",
      "Logistiek"
    ],
    "oorzaak_raw": "Cause: Personeel, Logistiek",
    "terminus_alert": null,
    "advies": null,
    "haltes": [
      {
        "halte_id": "NL:S:37223552",
        "halte_naam": "De Vlinder",
        "geplande_tijd": "10:34",
        "vertraging_min": 0,
        "status": "cancelled",
        "vertrokken": false,
        "realtime": false,
        "platform": "Perron E",
        "bestemming": "Amsterdam Noord"
      }
    ],
    "eerste_tijd": "10:34",
    "dagdeel": "dal",
    "bijgewerkt": "2026-07-12 08:30:57",
    "eerst_gezien": "2026-07-12 08:30:57"
  },
  {
    "id": "EBS:1067:7000_2026-07-12",
    "journey_id": "EBS:1067:7000",
    "datum": "2026-07-12",
    "lijn": "67",
    "lijnkleur": "#004899",
    "categorie": "M-net",
    "status": "cancelled",
    "oorzaak_categorieen": [
      "Personeel",
      "Logistiek"
    ],
    "oorzaak_raw": "Cause: Personeel, Logistiek",
    "terminus_alert": null,
    "advies": null,
    "haltes": [
      {
        "halte_id": "NL:S:37220130",
        "halte_naam": "Station Zaandam (Provincialeweg)",
        "geplande_tijd": "08:20",
        "vertraging_min": 0,
        "status": "cancelled",
        "vertrokken": false,
        "realtime": false,
        "platform": "Perron A",
        "bestemming": "Purmerend via Wormerveer"
      }
    ],
    "eerste_tijd": "08:20",
    "dagdeel": "ochtendspits",
    "bijgewerkt": "2026-07-12 06:15:36",
    "eerst_gezien": "2026-07-12 06:15:36"
  }
]